activipy/pgsql/__init__.py
activipy/pgsql/pgsql.py
activipy/pgsql/tests/__init__.py
activipy/pgsql/tests/test_simple.py
activipy_pgsql-0.1.0.dist-info/DESCRIPTION.rst
activipy_pgsql-0.1.0.dist-info/METADATA
activipy_pgsql-0.1.0.dist-info/RECORD
activipy_pgsql-0.1.0.dist-info/WHEEL
activipy_pgsql-0.1.0.dist-info/entry_points.txt
activipy_pgsql-0.1.0.dist-info/metadata.json
activipy_pgsql-0.1.0.dist-info/top_level.txt
