Metadata-Version: 2.0
Name: activipy-pgsql
Version: 0.1.0
Summary: A PostgreSQL Environment for Activipy
Home-page: https://src.coalesco.ca/w3c-social/activipy_pgsql
Author: Coalesco Digital Systems Inc. - Mark Shane Hayden
Author-email: mhayden@coalesco.ca
License: Apache Software License 2.0, GPLv3+
Keywords: activitystream postgresql environment
Platform: UNKNOWN
Classifier: Development Status :: 3 - Alpha
Classifier: Intended Audience :: Developers
Classifier: Topic :: Communications
Classifier: Topic :: Software Development :: Libraries
Classifier: License :: OSI Approved :: Apache Software License
Classifier: License :: OSI Approved :: GNU General Public License v3 or later (GPLv3+)
Classifier: Programming Language :: Python :: 3
Requires-Dist: activipy
Requires-Dist: psycopg2
Provides-Extra: dev
Requires-Dist: check-manifest; extra == 'dev'
Provides-Extra: test
Requires-Dist: coverage; extra == 'test'
